<extension implements="::fwServices::registry::AppConfig2">
    <id>ImageManager</id>
    <parameters>
        <param name="WID_PARENT" />
        <param name="GENERIC_UID" />
        <param name="IMAGE_UID" /><!-- Image to manage -->
        <param name="TF_IMAGE" /><!-- Composite containing the selected TransferFunction -->
        <param name="TF_KEY" default="SelectedTF"/><!-- Key of the TransferFunction in the composite 'TF_IMAGE' -->
    </parameters>
    <config>

        <object uid="${IMAGE_UID}" type="::fwData::Image" src="ref" />
        <object uid="${TF_IMAGE}" type="::fwData::Composite" src="ref" />

        <service uid="imageManagerView" type="::gui::view::SDefaultView">
            <gui>
                <layout type="::fwGui::LineLayoutManager">
                    <orientation value="vertical" />
                    <view proportion="0" />
                    <view proportion="0" />
                    <spacer />
                </layout>
            </gui>
            <registry>
                <parent wid="${WID_PARENT}" />
                <view sid="windowLevelImage" start="yes" />
                <view sid="sliderView" start="yes" />
            </registry>
        </service>

        <service uid="sliderView" type="::gui::view::SDefaultView">
            <gui>
                <layout type="::fwGui::LineLayoutManager">
                    <orientation value="horizontal" />
                    <view proportion="1" />
                </layout>
            </gui>
            <registry>
                <view sid="selectorSliderNegatoImage" start="yes" />
            </registry>
        </service>

        <!-- Service to add field used to properly display and manage image: Slice index, TransferFunction, ... -->
        <service uid="medicalImageConverterImage" type="::ctrlSelection::MedicalImageSrv">
            <inout key="image" uid="${IMAGE_UID}" />
        </service>

        <!-- Editor to manage slice index and image orientation (axial, frontal, sagittal) -->
        <service uid="selectorSliderNegatoImage" type="::uiImageQt::SliceIndexPositionEditor" autoConnect="yes">
            <inout key="image" uid="${IMAGE_UID}" />
            <sliceIndex>axial</sliceIndex>
        </service>

        <!-- Editor to manage image windowing -->
        <service uid="windowLevelImage" type="::uiImageQt::WindowLevel" autoConnect="yes">
            <inout key="image" uid="${IMAGE_UID}" />
            <inout key="TFSelections" uid="${TF_IMAGE}" />
            <config selectedTFKey="${TF_KEY}" />
        </service>
        
        <start uid="imageManagerView" />
        <start uid="medicalImageConverterImage" />
        
    </config>
</extension>
